chestella/__init__.py
chestella/__main__.py
chestella/chestella.py
chestella/directory/Directory.py
chestella/directory/__init__.py
chestella/makefile/Makefile.py
chestella/makefile/__init__.py
chestella/makefile/config.py
chestella/project/Project.py
chestella/project/__init__.py
chestella/project/config.py
chestella-0.4.dist-info/DESCRIPTION.rst
chestella-0.4.dist-info/METADATA
chestella-0.4.dist-info/RECORD
chestella-0.4.dist-info/WHEEL
chestella-0.4.dist-info/entry_points.txt
chestella-0.4.dist-info/metadata.json
chestella-0.4.dist-info/top_level.txt
