Metadata-Version: 2.0
Name: chestella
Version: 0.4
Summary: A C-Projects manager
Home-page: https://github.com/LucianoFromTrelew/chestella
Author: Luciano Serruya Aloisi
Author-email: lucianoserruya@hotmail.com
License: UNKNOWN
Download-URL: https://github.com/LucianoFromTrelew/chestella/archive/0.1.tar.gz
Keywords: project,C,c,creator,manager
Platform: UNKNOWN
